pygen_structures/__init__.py
pygen_structures/__main__.py
pygen_structures/_functions_const.py
pygen_structures/_typing.py
pygen_structures/charmm_containers.py
pygen_structures/convenience_functions.py
pygen_structures/version.py
pygen_structures/mol_containers/__init__.py
pygen_structures/mol_containers/atom.py
pygen_structures/mol_containers/molecule.py
pygen_structures/mol_containers/structure.py
pygen_structures/test/.coverage
pygen_structures/test/__init__.py
pygen_structures/test/charmm_dir.pkl
pygen_structures/test/test_charmm_containers.py
pygen_structures/test/test_command_line.py
pygen_structures/test/test_convenience_functions.py
pygen_structures/test/test_mol_containers.py
pygen_structures/test/test_openmm.py
pygen_structures/test/test_toppar/par_all36_prot.prm
pygen_structures/test/test_toppar/top_all36_prot.rtf
pygen_structures/test/test_toppar/toppar_all36_prot_c36_d_aminoacids.str
pygen_structures/toppar/00changes_2018_to_2019.txt
pygen_structures/toppar/00git_information.txt
pygen_structures/toppar/00toppar_file_format.txt
pygen_structures/toppar/README.md
pygen_structures/toppar/par_all35_ethers.prm
pygen_structures/toppar/par_all36_carb.prm
pygen_structures/toppar/par_all36_cgenff.prm
pygen_structures/toppar/par_all36_lipid.prm
pygen_structures/toppar/par_all36_na.prm
pygen_structures/toppar/par_all36_prot.prm
pygen_structures/toppar/par_all36m_prot.prm
pygen_structures/toppar/top_all35_ethers.rtf
pygen_structures/toppar/top_all36_carb.rtf
pygen_structures/toppar/top_all36_cgenff.rtf
pygen_structures/toppar/top_all36_lipid.rtf
pygen_structures/toppar/top_all36_na.rtf
pygen_structures/toppar/top_all36_prot.rtf
pygen_structures/toppar/toppar_all.history
pygen_structures/toppar/toppar_water_ions.str
pygen_structures/toppar/stream/carb/toppar_all36_carb_glycolipid.str
pygen_structures/toppar/stream/carb/toppar_all36_carb_glycopeptide.str
pygen_structures/toppar/stream/carb/toppar_all36_carb_imlab.str
pygen_structures-0.2.5.dist-info/LICENSE
pygen_structures-0.2.5.dist-info/METADATA
pygen_structures-0.2.5.dist-info/WHEEL
pygen_structures-0.2.5.dist-info/entry_points.txt
pygen_structures-0.2.5.dist-info/top_level.txt
pygen_structures-0.2.5.dist-info/RECORD
