Metadata-Version: 2.1
Name: pygen-structures
Version: 0.2.5
Summary: 3D molecular structure generation for MD simulation
Home-page: https://github.com/thesketh/pygen-structures
Author: Travis Hesketh
Author-email: travis@hesketh.scot
License: UNKNOWN
Platform: UNKNOWN
Classifier: Programming Language :: Python :: 3
Classifier: Programming Language :: Python :: 3.7
Classifier: Development Status :: 4 - Beta
Classifier: Environment :: Console
Classifier: Intended Audience :: Science/Research
Classifier: Topic :: Scientific/Engineering :: Chemistry
Classifier: License :: OSI Approved :: BSD License
Classifier: Operating System :: OS Independent
Classifier: Typing :: Typed
Requires-Python: >=3.6,<3.8
Requires-Dist: numpy
